Metadata-Version: 1.1
Name: cms-estate
Version: 1.0.6
Summary: Best CMS for website of Real Estate agency. FREE! Reservation calendar, Mobile version, SEO, Admin panel , Classified ads. Django + ReactJS.
Home-page: https://github.com/reactpython/best_script_for_agencies
Author: ReactScripts
Author-email: imconfirmer@gmail.com
License: Apache License 2.0
Download-URL: https://github.com/reactpython/best_script_for_agencies
Keywords: property vacation real estate agency script cms system website plugin widget extension library airbnb saas cms crm script themeforest wordpress woocommerce drupal instagram facebook monstertemplates python reactjs django python
Platform: UNKNOWN
Classifier: Development Status :: 4 - Beta
Classifier: Environment :: Console
Classifier: Intended Audience :: Developers
Classifier: Intended Audience :: Science/Research
Classifier: License :: OSI Approved :: Apache Software License
Classifier: Operating System :: MacOS
Classifier: Operating System :: Microsoft
Classifier: Operating System :: POSIX :: Linux
Classifier: Programming Language :: Python :: 2.7
Classifier: Programming Language :: Python :: 3.0
Classifier: Programming Language :: Python :: 3.1
Classifier: Programming Language :: Python :: 3.2
Classifier: Programming Language :: Python :: 3.3
Classifier: Programming Language :: Python :: 3.4
Classifier: Programming Language :: Python :: 3.5
Classifier: Programming Language :: Python :: 3.6
Classifier: Topic :: Internet
Classifier: Topic :: Scientific/Engineering :: Information Analysis
